roadheader/__init__.py
roadheader/playwright_Rh.py
roadheader/roadheader.py
roadheader-0.1.0.dist-info/LICENSE
roadheader-0.1.0.dist-info/METADATA
roadheader-0.1.0.dist-info/WHEEL
roadheader-0.1.0.dist-info/top_level.txt
roadheader-0.1.0.dist-info/RECORD
