Metadata-Version: 2.1
Name: roadheader
Version: 0.1.0
Summary: A simple web crawler framework
Home-page: https://github.com/iridesc/roadheader
Author: Irid
Author-email: irid.zzy@gmail.com
Classifier: Programming Language :: Python :: 3
Classifier: License :: OSI Approved :: MIT License
Classifier: Operating System :: OS Independent
Requires-Python: >=3.6
License-File: LICENSE
Requires-Dist: setuptools
Requires-Dist: playwright
Requires-Dist: playwright_stealth
